bambu_lab_cloud_api-1.0.2.dist-info/licenses/LICENSE
bambulab/__init__.py
bambulab/auth.py
bambulab/client.py
bambulab/local_api.py
bambulab/models.py
bambulab/mqtt.py
bambulab/utils.py
bambulab/video.py
cli_tools/__init__.py
cli_tools/camera_viewer.py
cli_tools/monitor.py
cli_tools/query.py
servers/__init__.py
servers/compatibility.py
servers/compatibility_config.json.example
servers/proxy.py
servers/proxy_tokens.json.example
bambu_lab_cloud_api-1.0.2.dist-info/METADATA
bambu_lab_cloud_api-1.0.2.dist-info/WHEEL
bambu_lab_cloud_api-1.0.2.dist-info/entry_points.txt
bambu_lab_cloud_api-1.0.2.dist-info/top_level.txt
bambu_lab_cloud_api-1.0.2.dist-info/RECORD
