Metadata-Version: 2.4
Name: bambu-lab-cloud-api
Version: 1.0.2
Summary: Python library for Bambu Lab 3D printer Cloud API, MQTT, and local connections
Author: Bambu Lab API Contributors
License: AGPL-3.0
Project-URL: Homepage, https://github.com/coelacant1/Bambu-Lab-Cloud-API
Project-URL: Documentation, https://github.com/coelacant1/Bambu-Lab-Cloud-API#readme
Project-URL: Repository, https://github.com/coelacant1/Bambu-Lab-Cloud-API
Project-URL: Issues, https://github.com/coelacant1/Bambu-Lab-Cloud-API/issues
Keywords: bambu,bambulab,3dprinting,api,mqtt
Classifier: Development Status :: 4 - Beta
Classifier: Intended Audience :: Developers
Classifier: License :: OSI Approved :: GNU Affero General Public License v3
Classifier: Programming Language :: Python :: 3
Classifier: Programming Language :: Python :: 3.9
Classifier: Programming Language :: Python :: 3.10
Classifier: Programming Language :: Python :: 3.11
Classifier: Programming Language :: Python :: 3.12
Classifier: Programming Language :: Python :: 3.13
Classifier: Topic :: Software Development :: Libraries :: Python Modules
Classifier: Topic :: System :: Hardware
Requires-Python: >=3.9
License-File: LICENSE
Requires-Dist: requests>=2.25.0
Requires-Dist: paho-mqtt>=1.6.0
Provides-Extra: server
Requires-Dist: flask>=2.0.0; extra == "server"
Requires-Dist: flask-cors>=3.0.0; extra == "server"
Provides-Extra: dev
Requires-Dist: pytest>=7.0.0; extra == "dev"
Requires-Dist: pytest-cov>=4.0.0; extra == "dev"
Provides-Extra: all
Requires-Dist: flask>=2.0.0; extra == "all"
Requires-Dist: flask-cors>=3.0.0; extra == "all"
Requires-Dist: pytest>=7.0.0; extra == "all"
Requires-Dist: pytest-cov>=4.0.0; extra == "all"
Dynamic: license-file
